README.md
setup.py
hytools/__init__.py
hytools/meg_utils.py
hytools/vtc_utils.py
hytools.egg-info/PKG-INFO
hytools.egg-info/SOURCES.txt
hytools.egg-info/dependency_links.txt
hytools.egg-info/not-zip-safe
hytools.egg-info/top_level.txt