Metadata-Version: 1.0
Name: hytools
Version: 0.0.7
Summary: Tools for MEG and behavioural analysis
Home-page: http://github.com/hyruuk/hytools
Author: Yann Harel
Author-email: yharel109@gmail.com
License: UNKNOWN
Platform: UNKNOWN
